np_vba-0.13.2.dist-info/METADATA
np_vba-0.13.2.dist-info/WHEEL
np_vba-0.13.2.dist-info/licenses/LICENSE
visual_behavior/__init__.py
visual_behavior/analyze.py
visual_behavior/change_detection/__init__.py
visual_behavior/change_detection/licks/__init__.py
visual_behavior/change_detection/metadata/__init__.py
visual_behavior/change_detection/rewards/__init__.py
visual_behavior/change_detection/running/__init__.py
visual_behavior/change_detection/running/metrics.py
visual_behavior/change_detection/trials/__init__.py
visual_behavior/change_detection/trials/masks.py
visual_behavior/change_detection/trials/session_metrics.py
visual_behavior/change_detection/trials/summarize.py
visual_behavior/change_detection/trials/validation.py
visual_behavior/data_access/__init__.py
visual_behavior/data_access/filtering.py
visual_behavior/data_access/from_lims.py
visual_behavior/data_access/from_lims_utilities.py
visual_behavior/data_access/loading.py
visual_behavior/data_access/pre_post_conditions.py
visual_behavior/data_access/processing.py
visual_behavior/data_access/reformat.py
visual_behavior/data_access/utilities.py
visual_behavior/database.py
visual_behavior/devices.py
visual_behavior/dimensionality_reduction/__init__.py
visual_behavior/dimensionality_reduction/clustering/__init__.py
visual_behavior/dimensionality_reduction/clustering/figures.py
visual_behavior/dimensionality_reduction/clustering/plotting.py
visual_behavior/dimensionality_reduction/clustering/processing.py
visual_behavior/dimensionality_reduction/tca/plotting.py
visual_behavior/dimensionality_reduction/tca/processing.py
visual_behavior/encoder_processing/__init__.py
visual_behavior/encoder_processing/running_data_smoothing.py
visual_behavior/metrics.py
visual_behavior/ophys/__init__.py
visual_behavior/ophys/container_analysis/__init__.py
visual_behavior/ophys/container_analysis/utilities.py
visual_behavior/ophys/dataset/__init__.py
visual_behavior/ophys/dataset/cell_matching_dataset.py
visual_behavior/ophys/dataset/extended_stimulus_processing.py
visual_behavior/ophys/dataset/stimulus_processing.py
np_vba-0.13.2.dist-info/RECORD
