Metadata-Version: 2.1
Name: np-vba
Version: 0.13.2
Summary: Python package for analyzing behavioral data for Brain Observatory: Visual Behavior. Forked to specify dependencies in pyproject.toml and support Python >3.7.
Author-Email: Marina Garrett <marinag@alleninstitute.org>, Doug Ollerenshaw <dougo@alleninstitute.org>
Maintainer-Email: Ben Hardcastle <ben.hardcastle@alleninstitute.org>
License: Allen Institute Software License – This software license is the 2-clause BSD 
Classifier: Programming Language :: Python :: 3
Classifier: Programming Language :: Python :: 3.8
Classifier: Programming Language :: Python :: 3.9
Classifier: Programming Language :: Python :: 3.10
Classifier: Programming Language :: Python :: 3.11
Requires-Python: >=3.8
Requires-Dist: allensdk>=2.15.0
Requires-Dist: scikit-learn>=1.2.2
Requires-Dist: python-dateutil>=2.8.2
Requires-Dist: zipfile36>=0.1.3
Requires-Dist: pymongo>=4.3.3
Requires-Dist: pyyaml>=6.0
Requires-Dist: dash>=2.9.2
Requires-Dist: plotly>=5.14.1
Requires-Dist: hdmf>=3.4.7
Requires-Dist: h5py>=3.8.0
Requires-Dist: umap>=0.1.1
Requires-Dist: opencv-python-headless>=4.7.0.72
Requires-Dist: pytest; extra == "dev"
Requires-Dist: pytest-cov; extra == "dev"
Requires-Dist: coverage[toml]>=7.2.2; extra == "dev"
Requires-Dist: pdm>=2.4.9; extra == "dev"
Requires-Dist: flake8; extra == "dev"
Requires-Dist: pytest-html; extra == "dev"
Requires-Dist: markupsafe==2.0.1; extra == "dev"
Provides-Extra: dev
